<?xml version="1.0" encoding="UTF-8"?>
<GenRun Id="impl_1" LaunchPart="xc7s25csga225-1" LaunchTime="1747658686">
  <File Type="OPT-HWDEF" Name="blinker_v3.hwdef"/>
  <File Type="ROUTE-BUS-SKEW" Name="blinker_v3_bus_skew_routed.rpt"/>
  <File Type="PA-DCP" Name="blinker_v3.dcp"/>
  <File Type="ROUTE-PWR" Name="blinker_v3_power_routed.rpt"/>
  <File Type="PA-TCL" Name="blinker_v3.tcl"/>
  <File Type="OPT-METHODOLOGY-DRC" Name="blinker_v3_methodology_drc_opted.rpt"/>
  <File Type="INIT-TIMING" Name="blinker_v3_timing_summary_init.rpt"/>
  <File Type="ROUTE-PWR-SUM" Name="blinker_v3_power_summary_routed.pb"/>
  <File Type="OPT-RQA-PB" Name="blinker_v3_rqa_opted.pb"/>
  <File Type="REPORTS-TCL" Name="blinker_v3_reports.tcl"/>
  <File Type="OPT-DCP" Name="blinker_v3_opt.dcp"/>
  <File Type="OPT-DRC" Name="blinker_v3_drc_opted.rpt"/>
  <File Type="OPT-TIMING" Name="blinker_v3_timing_summary_opted.rpt"/>
  <File Type="PWROPT-DCP" Name="blinker_v3_pwropt.dcp"/>
  <File Type="PWROPT-DRC" Name="blinker_v3_drc_pwropted.rpt"/>
  <File Type="PWROPT-TIMING" Name="blinker_v3_timing_summary_pwropted.rpt"/>
  <File Type="PLACE-DCP" Name="blinker_v3_placed.dcp"/>
  <File Type="PLACE-IO" Name="blinker_v3_io_placed.rpt"/>
  <File Type="PLACE-CLK" Name="blinker_v3_clock_utilization_placed.rpt"/>
  <File Type="PLACE-UTIL" Name="blinker_v3_utilization_placed.rpt"/>
  <File Type="PLACE-UTIL-PB" Name="blinker_v3_utilization_placed.pb"/>
  <File Type="PLACE-CTRL" Name="blinker_v3_control_sets_placed.rpt"/>
  <File Type="PLACE-SIMILARITY" Name="blinker_v3_incremental_reuse_placed.rpt"/>
  <File Type="PLACE-PRE-SIMILARITY" Name="blinker_v3_incremental_reuse_pre_placed.rpt"/>
  <File Type="BG-BIN" Name="blinker_v3.bin"/>
  <File Type="PLACE-TIMING" Name="blinker_v3_timing_summary_placed.rpt"/>
  <File Type="ROUTE-PWR-RPX" Name="blinker_v3_power_routed.rpx"/>
  <File Type="PLACE-RQA-PB" Name="blinker_v3_rqa_placed.pb"/>
  <File Type="POSTPLACE-PWROPT-DCP" Name="blinker_v3_postplace_pwropt.dcp"/>
  <File Type="BITSTR-MSK" Name="blinker_v3.msk"/>
  <File Type="POSTPLACE-PWROPT-TIMING" Name="blinker_v3_timing_summary_postplace_pwropted.rpt"/>
  <File Type="PHYSOPT-DCP" Name="blinker_v3_physopt.dcp"/>
  <File Type="PHYSOPT-DRC" Name="blinker_v3_drc_physopted.rpt"/>
  <File Type="BITSTR-RBT" Name="blinker_v3.rbt"/>
  <File Type="PHYSOPT-TIMING" Name="blinker_v3_timing_summary_physopted.rpt"/>
  <File Type="ROUTE-ERROR-DCP" Name="blinker_v3_routed_error.dcp"/>
  <File Type="ROUTE-DCP" Name="blinker_v3_routed.dcp"/>
  <File Type="ROUTE-BLACKBOX-DCP" Name="blinker_v3_routed_bb.dcp"/>
  <File Type="ROUTE-DRC" Name="blinker_v3_drc_routed.rpt"/>
  <File Type="ROUTE-DRC-PB" Name="blinker_v3_drc_routed.pb"/>
  <File Type="ROUTE-DRC-RPX" Name="blinker_v3_drc_routed.rpx"/>
  <File Type="ROUTE-METHODOLOGY-DRC" Name="blinker_v3_methodology_drc_routed.rpt"/>
  <File Type="ROUTE-METHODOLOGY-DRC-RPX" Name="blinker_v3_methodology_drc_routed.rpx"/>
  <File Type="ROUTE-METHODOLOGY-DRC-PB" Name="blinker_v3_methodology_drc_routed.pb"/>
  <File Type="ROUTE-RQS-PB" Name="blinker_v3_rqs_routed.pb"/>
  <File Type="ROUTE-STATUS" Name="blinker_v3_route_status.rpt"/>
  <File Type="ROUTE-STATUS-PB" Name="blinker_v3_route_status.pb"/>
  <File Type="ROUTE-TIMINGSUMMARY" Name="blinker_v3_timing_summary_routed.rpt"/>
  <File Type="ROUTE-TIMING-PB" Name="blinker_v3_timing_summary_routed.pb"/>
  <File Type="ROUTE-TIMING-RPX" Name="blinker_v3_timing_summary_routed.rpx"/>
  <File Type="ROUTE-SIMILARITY" Name="blinker_v3_incremental_reuse_routed.rpt"/>
  <File Type="ROUTE-CLK" Name="blinker_v3_clock_utilization_routed.rpt"/>
  <File Type="ROUTE-BUS-SKEW-PB" Name="blinker_v3_bus_skew_routed.pb"/>
  <File Type="ROUTE-BUS-SKEW-RPX" Name="blinker_v3_bus_skew_routed.rpx"/>
  <File Type="POSTROUTE-PHYSOPT-DCP" Name="blinker_v3_postroute_physopt.dcp"/>
  <File Type="POSTROUTE-PHYSOPT-BLACKBOX-DCP" Name="blinker_v3_postroute_physopt_bb.dcp"/>
  <File Type="POSTROUTE-PHYSOPT-TIMING" Name="blinker_v3_timing_summary_postroute_physopted.rpt"/>
  <File Type="POSTROUTE-PHYSOPT-TIMING-PB" Name="blinker_v3_timing_summary_postroute_physopted.pb"/>
  <File Type="POSTROUTE-PHYSOPT-TIMING-RPX" Name="blinker_v3_timing_summary_postroute_physopted.rpx"/>
  <File Type="POSTROUTE-PHYSOPT-BUS-SKEW" Name="blinker_v3_bus_skew_postroute_physopted.rpt"/>
  <File Type="BG-BIT" Name="blinker_v3.bit"/>
  <File Type="POSTROUTE-PHYSOPT-BUS-SKEW-PB" Name="blinker_v3_bus_skew_postroute_physopted.pb"/>
  <File Type="POSTROUTE-PHYSOPT-BUS-SKEW-RPX" Name="blinker_v3_bus_skew_postroute_physopted.rpx"/>
  <File Type="BITSTR-NKY" Name="blinker_v3.nky"/>
  <File Type="BITSTR-BMM" Name="blinker_v3_bd.bmm"/>
  <File Type="BITSTR-MMI" Name="blinker_v3.mmi"/>
  <File Type="PDI-FILE" Name="blinker_v3.pdi"/>
  <File Type="BOOT-PDI-FILE" Name="blinker_v3_boot.pdi"/>
  <File Type="PL-PDI-FILE" Name="blinker_v3_pld.pdi"/>
  <File Type="RCFI_FILE" Name="blinker_v3.rcfi"/>
  <File Type="CFI_FILE" Name="blinker_v3.cfi"/>
  <File Type="RNPI_FILE" Name="blinker_v3.rnpi"/>
  <File Type="NPI_FILE" Name="blinker_v3.npi"/>
  <File Type="RBD_FILE" Name="blinker_v3.rbd"/>
  <File Type="BITSTR-LTX" Name="debug_nets.ltx"/>
  <File Type="BITSTR-LTX" Name="blinker_v3.ltx"/>
  <File Type="BITSTR-SYSDEF" Name="blinker_v3.sysdef"/>
  <File Type="BG-BGN" Name="blinker_v3.bgn"/>
  <File Type="BG-DRC" Name="blinker_v3.drc"/>
  <File Type="RDI-RDI" Name="blinker_v3.vdi"/>
  <File Type="WBT-USG" Name="usage_statistics_webtalk.html"/>
  <File Type="ROUTE-RQS" Name="blinker_v3_routed.rqs"/>
  <File Type="POSTROUTE-PHYSOPT-RQS" Name="blinker_v3_postroute_physopted.rqs"/>
  <File Type="ROUTE-RQS-RPT" Name="route_report_qor_suggestions_0.rpt"/>
  <File Type="POSTROUTE-PHYSOPT-RQS-RPT" Name="postroute_physopt_report_qor_suggestions_0.rpt"/>
  <FileSet Name="sources" Type="DesignSrcs" RelSrcDir="$PSRCDIR/sources_1" RelGenDir="$PGENDIR/sources_1">
    <Filter Type="Srcs"/>
    <File Path="$PSRCDIR/sources_1/imports/vhdlscripts/blinker_v3.vhd">
      <FileInfo>
        <Attr Name="ImportPath" Val="$PPRDIR/../../../../../Users/ASUS/Desktop/Lab0/vhdlscripts/blinker_v3.vhd"/>
        <Attr Name="ImportTime" Val="1747582953"/>
        <Attr Name="UsedIn" Val="synthesis"/>
        <Attr Name="UsedIn" Val="simulation"/>
      </FileInfo>
    </File>
    <Config>
      <Option Name="DesignMode" Val="RTL"/>
      <Option Name="TopModule" Val="blinker_v3"/>
      <Option Name="TopAutoSet" Val="TRUE"/>
    </Config>
  </FileSet>
  <FileSet Name="constrs_in" Type="Constrs" RelSrcDir="$PSRCDIR/constrs_1" RelGenDir="$PGENDIR/constrs_1">
    <Filter Type="Constrs"/>
    <File Path="$PSRCDIR/constrs_1/imports/SpartanConstraints/Cmod-S7-25-Master.xdc">
      <FileInfo>
        <Attr Name="ImportPath" Val="$PPRDIR/../../../../../Users/ASUS/Desktop/Lab0/SpartanConstraints/Cmod-S7-25-Master.xdc"/>
        <Attr Name="ImportTime" Val="1715188526"/>
        <Attr Name="UsedIn" Val="synthesis"/>
        <Attr Name="UsedIn" Val="implementation"/>
      </FileInfo>
    </File>
    <Config>
      <Option Name="ConstrsType" Val="XDC"/>
    </Config>
  </FileSet>
  <FileSet Name="utils" Type="Utils" RelSrcDir="$PSRCDIR/utils_1" RelGenDir="$PGENDIR/utils_1">
    <Filter Type="Utils"/>
    <Config>
      <Option Name="TopAutoSet" Val="TRUE"/>
    </Config>
  </FileSet>
  <Strategy Version="1" Minor="2">
    <StratHandle Name="Vivado Implementation Defaults" Flow="Vivado Implementation 2024">
      <Desc>Default settings for Implementation.</Desc>
    </StratHandle>
    <Step Id="init_design"/>
    <Step Id="opt_design"/>
    <Step Id="power_opt_design"/>
    <Step Id="place_design"/>
    <Step Id="post_place_power_opt_design"/>
    <Step Id="phys_opt_design"/>
    <Step Id="route_design"/>
    <Step Id="post_route_phys_opt_design"/>
    <Step Id="write_bitstream"/>
  </Strategy>
</GenRun>
